autoplan/__init__.py
autoplan/chain.py
autoplan/cli.py
autoplan/core.py
autoplan/dependency.py
autoplan/execution_context.py
autoplan/func_utils.py
autoplan/generator/cookiecutter/cookiecutter.json
autoplan/generator/cookiecutter/hooks/post_gen_project.py
autoplan/generator/cookiecutter/{{cookiecutter.project_slug}}/README.md
autoplan/generator/cookiecutter/{{cookiecutter.project_slug}}/pyproject.toml
autoplan/generator/cookiecutter/{{cookiecutter.project_slug}}/{{cookiecutter.project_slug}}/app.py
autoplan/generator/cookiecutter/{{cookiecutter.project_slug}}/{{cookiecutter.project_slug}}/dependencies.py
autoplan/generator/cookiecutter/{{cookiecutter.project_slug}}/{{cookiecutter.project_slug}}/main.py
autoplan/generator/cookiecutter/{{cookiecutter.project_slug}}/{{cookiecutter.project_slug}}/tools/you_search.py
autoplan/llm_utils/create_partial_streaming_completion.py
autoplan/models.py
autoplan/phases/combine_steps.py
autoplan/phases/generate_plan.py
autoplan/results.py
autoplan/tool.py
autoplan/trace.py
autoplan-0.1.3.dist-info/LICENSE
autoplan-0.1.3.dist-info/METADATA
autoplan-0.1.3.dist-info/WHEEL
autoplan-0.1.3.dist-info/entry_points.txt
autoplan-0.1.3.dist-info/RECORD
