Metadata-Version: 2.1
Name: autoplan
Version: 0.1.3
Summary: AutoPlan is an open-source Python framework that provides a powerful pattern for implementing agentic AI applications, leveraging dynamic plan generation to select and use external tools based on the task's context.
Home-page: https://Institute-for-Advanced-Enterprise-AI.github.io/autoplan
License: MIT
Author: Dave Nachman
Author-email: dave.nachman.dev@gmail.com
Requires-Python: >=3.12,<4.0
Classifier: License :: OSI Approved :: MIT License
Classifier: Programming Language :: Python :: 3
Classifier: Programming Language :: Python :: 3.12
Requires-Dist: click (>=8.1.7,<9.0.0)
Requires-Dist: cookiecutter (>=2.6.0,<3.0.0)
Requires-Dist: httpx (>=0.27.2,<0.28.0)
Requires-Dist: httpx-sse (>=0.4.0,<0.5.0)
Requires-Dist: litellm (>=1.48.12,<2.0.0)
Requires-Dist: pydantic (>=2.9.0,<3.0.0)
Requires-Dist: pydantic-partial (>=0.5.5,<0.6.0)
Requires-Dist: python-dotenv (>=1.0.1,<2.0.0)
Requires-Dist: tenacity (>=9.0.0,<10.0.0)
Project-URL: Documentation, https://Institute-for-Advanced-Enterprise-AI.github.io/autoplan
Project-URL: Repository, https://github.com/Institute-for-Advanced-Enterprise-AI/autoplan
